funsketch/__init__.py
funsketch/db/__init__.py
funsketch/db/analyse.py
funsketch/db/episode.py
funsketch/db/sketch.py
funsketch/episode/__init__.py
funsketch/episode/update.py
funsketch/op/__init__.py
funsketch/op/analyse.py
funsketch/op/drive.py
funsketch/op/episode.py
funsketch/op/sketch.py
funsketch/sketch/__init__.py
funsketch/sketch/meta/__init__.py
funsketch/sketch/meta/meta.py
funsketch/sketch/task/__init__.py
funsketch/sketch/task/audio.py
funsketch/sketch/task/base.py
funsketch/sketch/task/load.py
funsketch/sketch/task/text.py
funsketch-1.0.61.dist-info/METADATA
funsketch-1.0.61.dist-info/WHEEL
funsketch-1.0.61.dist-info/top_level.txt
funsketch-1.0.61.dist-info/RECORD
